flask_pagedown/__init__.py
flask_pagedown/fields.py
flask_pagedown/widgets.py
Flask_PageDown-0.3.0.dist-info/LICENSE
Flask_PageDown-0.3.0.dist-info/METADATA
Flask_PageDown-0.3.0.dist-info/WHEEL
Flask_PageDown-0.3.0.dist-info/top_level.txt
Flask_PageDown-0.3.0.dist-info/RECORD
