Metadata-Version: 1.1
Name: Flask-PageDown
Version: 0.3.0
Summary: Implementation of StackOverflow's "PageDown" markdown editor for Flask-WTF.
Home-page: http://github.com/miguelgrinberg/flask-pagedown/
Author: Miguel Grinberg
Author-email: miguelgrinberg50@gmail.com
License: MIT
Platform: any
Classifier: Environment :: Web Environment
Classifier: Intended Audience :: Developers
Classifier: License :: OSI Approved :: MIT License
Classifier: Operating System :: OS Independent
Classifier: Programming Language :: Python
Classifier: Topic :: Internet :: WWW/HTTP :: Dynamic Content
Classifier: Topic :: Software Development :: Libraries :: Python Modules
